descriptions/__init__.py
descriptions/__main__.py
descriptions/descriptions_downloader.py
descriptions/exceptions.py
omim_descriptions-10.3.0rc2.dist-info/METADATA
omim_descriptions-10.3.0rc2.dist-info/WHEEL
omim_descriptions-10.3.0rc2.dist-info/top_level.txt
omim_descriptions-10.3.0rc2.dist-info/RECORD
