Metadata-Version: 2.1
Name: omim-descriptions
Version: 10.3.0rc2
Summary: This package is a library that provides descriptions (such as those from Wikipedia) to geographic objects.
Home-page: https://github.com/mapsme
Author: My.com B.V. (Mail.Ru Group)
Author-email: dev@maps.me
License: UNKNOWN
Platform: UNKNOWN
Classifier: Programming Language :: Python :: 3
Classifier: License :: OSI Approved :: Apache Software License
Requires-Python: >=3.6
Requires-Dist: htmlmin (==0.1.12)
Requires-Dist: requests (==2.23.0)
Requires-Dist: beautifulsoup4 (==4.9.1)
Requires-Dist: wikidata (==0.6.1)
Requires-Dist: wikipedia-api (==0.5.4)
